HISTORY.rst
LICENSE.rst
MANIFEST.in
README.rst
setup.py
src/collective/__init__.py
src/collective.awstats.egg-info/PKG-INFO
src/collective.awstats.egg-info/SOURCES.txt
src/collective.awstats.egg-info/dependency_links.txt
src/collective.awstats.egg-info/entry_points.txt
src/collective.awstats.egg-info/namespace_packages.txt
src/collective.awstats.egg-info/not-zip-safe
src/collective.awstats.egg-info/requires.txt
src/collective.awstats.egg-info/top_level.txt
src/collective/awstats/__init__.py
src/collective/awstats/config.py
src/collective/awstats/configure.zcml
src/collective/awstats/constants.py
src/collective/awstats/interfaces.py
src/collective/awstats/profiles.zcml
src/collective/awstats/provider.py
src/collective/awstats/vocabularies.py
src/collective/awstats/at/__init__.py
src/collective/awstats/at/awstats.py
src/collective/awstats/at/custompart.py
src/collective/awstats/at/extender.py
src/collective/awstats/browser/__init__.py
src/collective/awstats/browser/base.py
src/collective/awstats/browser/browsers.py
src/collective/awstats/browser/clients.py
src/collective/awstats/browser/configure.zcml
src/collective/awstats/browser/controlpanel.py
src/collective/awstats/browser/controlpanel.yaml
src/collective/awstats/browser/countries.py
src/collective/awstats/browser/custompart.py
src/collective/awstats/browser/datatypes.py
src/collective/awstats/browser/daysinmonth.py
src/collective/awstats/browser/interfaces.py
src/collective/awstats/browser/monthhistory.py
src/collective/awstats/browser/operatingsystems.py
src/collective/awstats/browser/overview.py
src/collective/awstats/browser/robots.py
src/collective/awstats/browser/servertime.py
src/collective/awstats/browser/sessions.py
src/collective/awstats/browser/siteurl.py
src/collective/awstats/browser/stats.py
src/collective/awstats/browser/statschooser.py
src/collective/awstats/browser/weekdays.py
src/collective/awstats/browser/images/Unknown-ico.png
src/collective/awstats/browser/images/awstats_icon.png
src/collective/awstats/browser/images/awstats_part_icon.png
src/collective/awstats/browser/images/bar_bg.png
src/collective/awstats/browser/images/bar_hor_bg.png
src/collective/awstats/browser/images/chrome-ico.png
src/collective/awstats/browser/images/css-ico.png
src/collective/awstats/browser/images/doc-ico.png
src/collective/awstats/browser/images/firefox-ico.png
