Metadata-Version: 1.1
Name: collective.awstats
Version: 1.0
Summary: AWStats in Plone
Home-page: http://pypi.python.org/pypi/collective.awstats
Author: BlueDynamics Alliance
Author-email: dev@bluedynamics.com
License: GPL
Keywords: plone statistics
Platform: UNKNOWN
Classifier: License :: OSI Approved :: GNU General Public License (GPL)
Classifier: Operating System :: OS Independent
Classifier: Programming Language :: Python
Classifier: Topic :: Software Development
